labdb/__init__.py
labdb/api.py
labdb/cli.py
labdb/cli_commands.py
labdb/cli_completions.py
labdb/cli_formatting.py
labdb/cli_interactive.py
labdb/cli_json_editor.py
labdb/config.py
labdb/database.py
labdb/serialization.py
labdb/utils.py
labdb-1.0.5.dist-info/licenses/LICENSE
labdb-1.0.5.dist-info/METADATA
labdb-1.0.5.dist-info/WHEEL
labdb-1.0.5.dist-info/entry_points.txt
labdb-1.0.5.dist-info/top_level.txt
labdb-1.0.5.dist-info/RECORD
