Metadata-Version: 2.4
Name: labdb
Version: 1.0.5
Summary: MongoDB experiment management tool
Author-email: Rohan Menon <rohanme@mit.edu>
License-Expression: MIT
Project-URL: Homepage, https://github.com/rmenon1008/labdb
Project-URL: Issues, https://github.com/rmenon1008/labdb/issues
Classifier: Programming Language :: Python :: 3
Classifier: Operating System :: OS Independent
Requires-Python: >=3.7
License-File: LICENSE
Requires-Dist: jsonschema~=4.23.0
Requires-Dist: prompt_toolkit~=3.0.50
Requires-Dist: Pygments~=2.19.1
Requires-Dist: pymongo~=4.11.3
Requires-Dist: PyYAML~=6.0.2
Requires-Dist: numpy>=1.26.1
Requires-Dist: argcomplete>=3.2.3
Requires-Dist: pyreadline3>=3.4.1; sys_platform == "win32"
Requires-Dist: lz4>=4.0.0
Dynamic: license-file
